virtualizorendpoint/__init__.py
virtualizorendpoint/api.py
virtualizorendpoint-0.6.dist-info/METADATA
virtualizorendpoint-0.6.dist-info/WHEEL
virtualizorendpoint-0.6.dist-info/RECORD
